aminoscribe/__init__.py
aminoscribe/aminoscribe.py
aminoscribe/generate_template.py
aminoscribe/data/amplitude_noise.csv
aminoscribe/data/sequences.pickle
aminoscribe/data/step_durations.csv
aminoscribe/data/step_sizes_in_aa.csv
aminoscribe-0.5.0.dist-info/licenses/LICENSE
aminoscribe-0.5.0.dist-info/METADATA
aminoscribe-0.5.0.dist-info/WHEEL
aminoscribe-0.5.0.dist-info/top_level.txt
aminoscribe-0.5.0.dist-info/RECORD
