Metadata-Version: 2.4
Name: aminoscribe
Version: 0.5.0
Summary: Amino Scribe is a Python package for generating nanopore squiggles based on protein sequences.
Author-email: Melissa Queen <melq@cs.washington.edu>
Maintainer-email: Melissa Queen <melq@cs.washington.edu>
License-Expression: CC-BY-NC-4.0
License-File: LICENSE
Requires-Dist: pandas
Requires-Dist: numpy
Requires-Dist: scipy
Dynamic: license-file
